deepdub/__init__.py
deepdub/__main__.py
deepdub/cli.py
deepdub/client.py
deepdub-0.1.17.dist-info/licenses/LICENSE
deepdub-0.1.17.dist-info/METADATA
deepdub-0.1.17.dist-info/WHEEL
deepdub-0.1.17.dist-info/entry_points.txt
deepdub-0.1.17.dist-info/top_level.txt
deepdub-0.1.17.dist-info/RECORD
