Metadata-Version: 2.4
Name: deepdub
Version: 0.1.17
Summary: A Python client for interacting with the Deepdub API
Author-email: Deepdub <info@deepdub.ai>
License: MIT
Project-URL: Homepage, https://github.com/deepdub-ai/deepdub
Project-URL: Bug Tracker, https://github.com/deepdub-ai/deepdub/issues
Keywords: deepdub,text-to-speech,tts,voice-cloning
Classifier: Development Status :: 3 - Alpha
Classifier: Intended Audience :: Developers
Classifier: Programming Language :: Python :: 3
Classifier: Programming Language :: Python :: 3.11
Requires-Python: >=3.9
License-File: LICENSE
Requires-Dist: audiosample>=2.2.10
Requires-Dist: websockets>=15.0.1
Requires-Dist: requests>=2.31.0
Requires-Dist: click>=8.1.8
Dynamic: license-file
